<?xml version="1.0" encoding="UTF-8" ?>
<r xmlns="http://pear.php.net/dtd/rest.release" xmlns:xsi="http://www.w3.org/2001/XMLSchema-instance" xmlns:xlink="http://www.w3.org/1999/xlink" xsi:schemaLocation="http://pear.php.net/dtd/rest.release http://pear.php.net/dtd/rest.release.xsd">
    <p xlink:href="/rest/p/net_cicindela">Net_Cicindela</p>
    <c>openpear.org</c>
    <v>0.1.0</v>
    <st>beta</st>
    <l>PHP License 3.01</l>
    <m>MugeSo</m>
    <s>ライブドア謹製レコメンドエンジン[http://code.google.com/p/cicindela2/:title=Cicindela]のWebAPIラッパ

レコメンドエンジン自作する人はこれと同じWebAPIで作ればみんな幸せになるんじゃないかな。</s>
    <d>ライブドア謹製レコメンドエンジン[http://code.google.com/p/cicindela2/:title=Cicindela]のWebAPIラッパ

レコメンドエンジン自作する人はこれと同じWebAPIで作ればみんな幸せになるんじゃないかな。</d>
    <da>2009-06-11 01:17:35</da>
    <n>------------------------------------------------------------------------
r949 | MugeSo | 2009-06-11 01:07:46 -0700 (Thu, 11 Jun 2009) | 1 line

Net_Cicindela?\229?\136?\157?\230?\156?\159?\227?\130?\179?\227?\131?\159?\227?\131?\131?\227?\131?\136
------------------------------------------------------------------------</n>
    <f>3035</f>
    <g>http://openpear.org/get/Net_Cicindela-0.1.0</g>
    <x xlink:href="package.0.1.0.xml"/>
</r>