<?xml version="1.0" encoding="UTF-8" ?>
<r xmlns="http://pear.php.net/dtd/rest.release" xmlns:xsi="http://www.w3.org/2001/XMLSchema-instance" xmlns:xlink="http://www.w3.org/1999/xlink" xsi:schemaLocation="http://pear.php.net/dtd/rest.release http://pear.php.net/dtd/rest.release.xsd">
    <p xlink:href="/rest/p/io_swf">IO_SWF</p>
    <c>openpear.org</c>
    <v>1.0.0</v>
    <st>stable</st>
    <l>PHP License 3.01</l>
    <m>yoya</m>
    <s>SWF バイナリを解釈/編集する為のライブラリです。  IO_Bit が必要です。主に Flash Lite を対象にしています。</s>
    <d>SWF バイナリを解釈/編集する為のライブラリです。  IO_Bit が必要です。主に Flash Lite を対象にしています。</d>
    <da>2010-08-16 16:49:02</da>
    <n>
- ヘッダ FrameSize の RECT twips を signed で処理するよう修正
- JPEG入れ替えサンプルで携帯でJPEG表示出来ないコード(元々コメントアウトしてた)を削除。
 </n>
    <f>3416</f>
    <g>http://openpear.org/get/IO_SWF-1.0.0</g>
    <x xlink:href="package.1.0.0.xml"/>
</r>